{"geometry": {"location_type": "APPROXIMATE", "bounds": {"northeast": {"lat": 43.6757405, "lng": -79.4889165}, "southwest": {"lat": 43.657937, "lng": -79.5132924}}, "viewport": {"northeast": {"lat": 43.6757405, "lng": -79.4889165}, "southwest": {"lat": 43.657937, "lng": -79.5132924}}, "location": {"lat": 43.6673705, "lng": -79.5013207}}, "address_components": [{"long_name": "Lambton", "types": ["neighborhood", "political"], "short_name": "Lambton"}, {"long_name": "York", "types": ["sublocality_level_1", "sublocality", "political"], "short_name": "York"}, {"long_name": "Toronto", "types": ["locality", "political"], "short_name": "Toronto"}, {"long_name": "Toronto Division", "types": ["administrative_area_level_2", "political"], "short_name": "Toronto Division"}, {"long_name": "Ontario", "types": ["administrative_area_level_1", "political"], "short_name": "ON"}, {"long_name": "Canada", "types": ["country", "political"], "short_name": "CA"}], "place_id": "ChIJ51OPD-k2K4gR5l5kLRJKXx8", "formatted_address": "Lambton, Toronto, ON, Canada", "types": ["neighborhood", "political"]}