{"geometry": {"location_type": "APPROXIMATE", "bounds": {"northeast": {"lat": 43.6792012, "lng": -79.4181275}, "southwest": {"lat": 43.6764544, "lng": -79.42232249999999}}, "viewport": {"northeast": {"lat": 43.6792012, "lng": -79.4181275}, "southwest": {"lat": 43.6764544, "lng": -79.42232249999999}}, "location": {"lat": 43.6779102, "lng": -79.4201015}}, "address_components": [{"long_name": "Wychwood Park", "types": ["neighborhood", "political"], "short_name": "Wychwood Park"}, {"long_name": "Old Toronto", "types": ["sublocality_level_1", "sublocality", "political"], "short_name": "Old Toronto"}, {"long_name": "Toronto", "types": ["locality", "political"], "short_name": "Toronto"}, {"long_name": "Toronto Division", "types": ["administrative_area_level_2", "political"], "short_name": "Toronto Division"}, {"long_name": "Ontario", "types": ["administrative_area_level_1", "political"], "short_name": "ON"}, {"long_name": "Canada", "types": ["country", "political"], "short_name": "CA"}, {"long_name": "M6G", "types": ["postal_code_prefix", "postal_code"], "short_name": "M6G"}], "place_id": "ChIJDyspaIE0K4gRhgAzCtKFysY", "formatted_address": "Wychwood Park, Toronto, ON M6G, Canada", "types": ["neighborhood", "political"]}