{"geometry": {"location_type": "APPROXIMATE", "bounds": {"northeast": {"lat": 43.6535901, "lng": -79.421196}, "southwest": {"lat": 43.6405476, "lng": -79.4441557}}, "viewport": {"northeast": {"lat": 43.6535901, "lng": -79.421196}, "southwest": {"lat": 43.6405476, "lng": -79.4441557}}, "location": {"lat": 43.6463408, "lng": -79.4281914}}, "address_components": [{"long_name": "Little Portugal", "types": ["neighborhood", "political"], "short_name": "Little Portugal"}, {"long_name": "Old Toronto", "types": ["sublocality_level_1", "sublocality", "political"], "short_name": "Old Toronto"}, {"long_name": "Toronto", "types": ["locality", "political"], "short_name": "Toronto"}, {"long_name": "Toronto Division", "types": ["administrative_area_level_2", "political"], "short_name": "Toronto Division"}, {"long_name": "Ontario", "types": ["administrative_area_level_1", "political"], "short_name": "ON"}, {"long_name": "Canada", "types": ["country", "political"], "short_name": "CA"}], "place_id": "ChIJFa6sc1Q0K4gRWNYCQRTS3iQ", "formatted_address": "Little Portugal, Toronto, ON, Canada", "types": ["neighborhood", "political"]}